PSWDGenerator/__init__.py
pswdgenerator-1.0.0.dist-info/licenses/LICENSE
pswdgenerator-1.0.0.dist-info/WHEEL
pswdgenerator-1.0.0.dist-info/METADATA
pswdgenerator-1.0.0.dist-info/RECORD
