Metadata-Version: 2.4
Name: PSWDGenerator
Version: 1.0.0
Summary: Generator-Password
Author: Den*Ram
License-Expression: MIT
License-File: LICENSE
